my_tool.py
app/__init__.py
app/__main__.py
app/application.py
convertool-1.0.0.dist-info/LICENSE
convertool-1.0.0.dist-info/METADATA
convertool-1.0.0.dist-info/WHEEL
convertool-1.0.0.dist-info/entry_points.txt
convertool-1.0.0.dist-info/top_level.txt
convertool-1.0.0.dist-info/RECORD
