Metadata-Version: 2.1
Name: convertool
Version: 1.0.0
Summary: <short description for the tool>
Author: Lee Seonghyun
Author-email: john.doe@foo.com
License: <the license you chose>
Classifier: Programming Language :: Python :: 3.8
Classifier: Operating System :: OS Independent
Requires-Python: >=3.7
License-File: LICENSE
Requires-Dist: bleach (==6.0.0)
Requires-Dist: certifi (==2023.7.22)
Requires-Dist: charset-normalizer (==3.2.0)
Requires-Dist: click (==8.1.7)
Requires-Dist: docutils (==0.20.1)
Requires-Dist: idna (==3.4)
Requires-Dist: importlib-metadata (==6.8.0)
Requires-Dist: jaraco.classes (==3.3.0)
Requires-Dist: keyring (==24.2.0)
Requires-Dist: markdown-it-py (==3.0.0)
Requires-Dist: mdurl (==0.1.2)
Requires-Dist: more-itertools (==10.1.0)
Requires-Dist: numpy (==1.25.2)
Requires-Dist: opencv-python (==4.8.0.76)
Requires-Dist: pkginfo (==1.9.6)
Requires-Dist: Pygments (==2.16.1)
Requires-Dist: readme-renderer (==41.0)
Requires-Dist: requests (==2.31.0)
Requires-Dist: requests-toolbelt (==1.0.0)
Requires-Dist: rfc3986 (==2.0.0)
Requires-Dist: rich (==13.5.2)
Requires-Dist: six (==1.16.0)
Requires-Dist: twine (==4.0.2)
Requires-Dist: urllib3 (==2.0.4)
Requires-Dist: webencodings (==0.5.1)
Requires-Dist: zipp (==3.16.2)
